rag_eval_suite/__init__.py
rag_eval_suite/data_models.py
rag_eval_suite/evaluator.py
rag_eval_suite/pipeline.py
rag_eval_suite/prompts.py
rag_eval_suite/synthesiser.py
rag_eval_suite/metrics/__init__.py
rag_eval_suite/metrics/generation.py
rag_eval_suite/metrics/retrieval.py
ragscope-0.1.0.dist-info/METADATA
ragscope-0.1.0.dist-info/WHEEL
ragscope-0.1.0.dist-info/top_level.txt
ragscope-0.1.0.dist-info/RECORD
