Metadata-Version: 2.4
Name: ragscope
Version: 0.1.0
Summary: A comprehensive suite for evaluating RAG pipelines.
Author-email: Harri Davies <harridavies03@gmail.com>
Project-URL: Homepage, https://github.com/c21051997/rag-eval-suite
Project-URL: Bug Tracker, https://github.com/c21051997/rag-eval-suite/issues
Classifier: Programming Language :: Python :: 3
Classifier: License :: OSI Approved :: MIT License
Classifier: Operating System :: OS Independent
Requires-Python: >=3.8
Requires-Dist: pydantic>=2.0
Requires-Dist: litellm>=1.0
Requires-Dist: rich>=13.0
Provides-Extra: dev
Requires-Dist: pytest; extra == "dev"
Requires-Dist: openai; extra == "dev"
Requires-Dist: anthropic; extra == "dev"
